{"inkVersion":21,"root":[["^Who are you?","\n","^How did you get here??","\n","^Well, it doesn’t matter, now you’re stuck here too","\n","^Where am I from?","\n","^You tell me!","\n","^I’ve always lived here, since the golden age of the forest","\n","^But during the war, I ended up, by accident, being trapped in this room…","\n","^Talk more about the war?","\n","^I dont't like to talk about it...","\n","^It was a huge trauma for everyone","\n","^A kid like you, wouldn't understand...","\n","^How did this all start?","\n","^Well, in the golden age, 3 great leaders ruled our society","\n","^But driven by greed, a betrayal happened","\n","^One of them, killed another leader...","\n","^And then, war has been declared…","\n","end",["done",{"#f":5,"#n":"g-0"}],null],"done",{"#f":1}],"listDefs":{}}